MANIFEST.in
README.rst
setup.py
./sergelab/__init__.py
./sergelab/utils/__init__.py
./sergelab/utils/setup.py
sergelab/__init__.py
sergelab.utils.egg-info/PKG-INFO
sergelab.utils.egg-info/SOURCES.txt
sergelab.utils.egg-info/dependency_links.txt
sergelab.utils.egg-info/namespace_packages.txt
sergelab.utils.egg-info/requires.txt
sergelab.utils.egg-info/top_level.txt
sergelab.utils.egg-info/zip-safe
sergelab/tests/test_manager.py
sergelab/utils/__init__.py
sergelab/utils/setup.py