Metadata-Version: 1.0
Name: sergelab.utils
Version: 0.11
Summary: Python utilities
Home-page: https://bitbucket.org/serge_brpr/sergelab.utils/
Author: Alexey Slynko, Sergey Syrov
Author-email: info@sergelab.ru
License: UNKNOWN
Platform: UNKNOWN
